wagtail_parler/__init__.py
wagtail_parler/apps.py
wagtail_parler/forms.py
wagtail_parler/handlers.py
wagtail_parler/models.py
wagtail_parler/settings.py
wagtail_parler/wagtail_hooks.py
wagtail_parler/admin/__init__.py
wagtail_parler/admin/columns.py
wagtail_parler/static/wagtail_parler/js/admin.js
wagtail_parler/templates/wagtail_parler/tables/languages_cell.html
wagtail_parler-0.7.3.dist-info/licenses/AUTHORS
wagtail_parler-0.7.3.dist-info/licenses/LICENSE
wagtail_parler_tests/__init__.py
wagtail_parler_tests/apps.py
wagtail_parler_tests/models.py
wagtail_parler_tests/settings.py
wagtail_parler_tests/tests.py
wagtail_parler_tests/urls.py
wagtail_parler_tests/wagtail_hooks.py
wagtail_parler_tests/migrations/0001_initial.py
wagtail_parler_tests/migrations/0002_auto_20230907_1910.py
wagtail_parler_tests/migrations/0003_food_latest_revision_and_more.py
wagtail_parler_tests/migrations/0004_ingredient_foodwithinlinepanel_and_more.py
wagtail_parler_tests/migrations/__init__.py
wagtail_parler-0.7.3.dist-info/METADATA
wagtail_parler-0.7.3.dist-info/WHEEL
wagtail_parler-0.7.3.dist-info/top_level.txt
wagtail_parler-0.7.3.dist-info/RECORD
