Metadata-Version: 2.4
Name: wagtail_parler
Version: 0.7.3
Summary: Brings "omelette du fromage" 🧀 from parler into wagtail 🐦 (via wagtail snippets or modeladmin)
Home-page: https://github.com/webu/wagtail-parler
Author: Webu
Author-email: contact@webu.coop
License: BSD-3-Clause
Project-URL: Source, https://github.com/webu/wagtail-parler
Project-URL: Tracker, https://github.com/webu/wagtail-parler/issues
Project-URL: Documentation, https://wagtail-parler.readthedocs.io/en/latest/
Classifier: Development Status :: 5 - Production/Stable
Classifier: Environment :: Web Environment
Classifier: Framework :: Django
Classifier: Intended Audience :: Developers
Classifier: License :: OSI Approved :: BSD License
Classifier: Operating System :: OS Independent
Classifier: Programming Language :: Python
Classifier: Programming Language :: Python :: 3
Classifier: Programming Language :: Python :: 3.9
Classifier: Programming Language :: Python :: 3.10
Classifier: Programming Language :: Python :: 3.11
Classifier: Framework :: Django
Classifier: Framework :: Django :: 4.2
Classifier: Framework :: Django :: 5.0
Classifier: Framework :: Wagtail
Classifier: Framework :: Wagtail :: 5
Classifier: Framework :: Wagtail :: 6
Classifier: Framework :: Wagtail :: 7
Classifier: Topic :: Internet :: WWW/HTTP
Classifier: Topic :: Internet :: WWW/HTTP :: Dynamic Content
Classifier: Topic :: Software Development :: Libraries :: Application Frameworks
Classifier: Topic :: Software Development :: Libraries :: Python Modules
Requires-Python: >=3.9
License-File: LICENSE
License-File: AUTHORS
Requires-Dist: Django>=4.2
Requires-Dist: wagtail>=5.0
Requires-Dist: django-parler>=2.3
Provides-Extra: testing
Requires-Dist: requests; extra == "testing"
Requires-Dist: beautifulsoup4; extra == "testing"
Requires-Dist: coverage>=3.7.0; extra == "testing"
Requires-Dist: black; extra == "testing"
Requires-Dist: flake8; extra == "testing"
Requires-Dist: mypy; extra == "testing"
Requires-Dist: types-requests; extra == "testing"
Dynamic: license-file
